{
    "id": "mirana",
    "title": "미라나 Mirana",
    "type": "민",
    "story": "왕족의 일원으로 태어나 태양계 왕좌의 차기 직계 공주였던 미라나는 달의 여신 셀레메네를 섬기고자 세속의 땅과 권리를 기꺼이 포기했다. 그 후 미라나는 달의 공주로 알려졌고, 은빛 밤의 숲을 거닐며 감히 여신의 성역인 은빛 연못에서 성스럽게 빛나는 연꽃을 훔치려는 자들을 감시한다. 거대한 야수의 등에 올라탄 미라나의 모습은 침착하고 당당하며 용맹스럽다. 미라나는 달의 변화와 별자리의 움직임에 맞춰 자신을 조율한다. 날카로운 월석 조각이 양 끝에 달린 미라나의 활은 달의 힘을 받아 빛의 화살을 만들어낸다.",
    "table": [
        ["이동속도", "300"],
        ["회전속도", "0.9"],
        ["시야", "1800 / 800"],
        ["공격 모션", "0.467+0.863"],
        ["공격 속도", "1.7"]
    ],
    "info": [
        "",
        ""
    ],
    "note": [
        ""
    ],
    "skill": [{
        "key": "Q",
        "img": "data/images/skill/mirana_starfall_hp2.png",
        "title": "유성우 Starstorm",
        "story": "달의 여신은 유사시에 우주의 층을 허물어 달의 공주에게 힘을 선사합니다.",
        "desc": "하늘에서 유성을 떨어뜨려 주위 적들에게 피해를 줍니다. 미라나에게서 175의 범위 내에 있는 적 중에서 무작위 적 1명이 유성우 공격력의 75%에 해당하는 피해를 받습니다.",
        "info": [
            ["마나 소모", "100/120/140/160"],
            ["쿨다운", "12"],
            ["능력", "대상 없음"],
            ["피해 유형", "마법"],
            ["주문 면역", "미관통"],
            ["피해", "75 / 150 / 225 / 300"],
            ["반경", "625"]
        ],
        "note": [
            "",
            ""
        ]
    }, {
        "key": "W",
        "img": "data/images/skill/mirana_arrow_hp2.png",
        "title": "신성한 화살 Sacred Arrow",
        "story": "달의 공주가 쏘는 화살은 달의 기운을 받아 아주 치명적입니다.",
        "desc": "필격의 명중률을 지닌 장거리 화살을 발사하여 가장 먼저 맞는 적에게 큰 피해를 주고 기절시킵니다. 기절 지속시간은 대상과의 거리에 따라 최소 0.01초에서 최대 5초까지 증가하며 최대 140의 보너스 피해가 적용됩니다.",
        "info": [
            ["마나 소모", "100/100/100/100"],
            ["쿨다운", "17"],
            ["능력", "목표 지점 지정"],
            ["피해 유형", "마법"],
            ["주문 면역", "미관통"],
            ["피해", "50 / 140 / 230 / 320"],
            ["범위", "3000"],
            ["최소 기절", "0.01"],
            ["최대 기절", "5"],
            ["최대 보너스 피해", "140"]
        ],
        "note": [
            "",
            ""
        ]
    }, {
        "key": "E",
        "img": "data/images/skill/mirana_leap_hp2.png",
        "title": "도약 Leap",
        "story": "미라나의 상징인 흰색 야수는 전장의 뜨거운 열기 속에서도 적과 아군 모두의 시선을 사로잡습니다.",
        "desc": "미라나가 전장에 뛰어듭니다. 격렬한 포효를 내질러 아군의 공격 속도와 이동 속도를 증가시킵니다. 공격 및 이동 속도 증가 효과는 10초 동안 지속됩니다.",
        "info": [
            ["마나 소모", "40/35/30/20"],
            ["쿨다운", "30/26/22/18"],
            ["능력", "대상 없음"],
            ["거리", "600 / 700 / 800 / 900"],
            ["이동 속도 보너스", "4% / 8% / 12% / 16%"],
            ["공격 속도 보너스", "8 / 16 / 24 / 32"]
        ],
        "note": [
            "",
            ""
        ]
    }, {
        "key": "R",
        "img": "data/images/skill/mirana_invis_hp2.png",
        "title": "달빛 그림자 Moonlight Shadow",
        "story": "셀레메네와 함께한 동안 미라나는 땅 위에 그림자를 드리워 아군을 숨기는 능력을 익혔습니다.",
        "desc": "미라나와 모든 아군 영웅을 투명하게 바꿉니다. 투명화 상태가 방해를 받았을 때 아직 달빛 그림자의 지속시간이 남아 있다면, 잠시 후 다시 투명 상태로 돌아갑니다. 침묵에 걸리면 다시 투명해지지 않습니다.",
        "info": [
            ["마나 소모", "75"],
            ["쿨다운", "140/120/100"],
            ["능력", "대상 없음"],
            ["투명화 지연시간", "2.5 / 2 / 1.5"],
            ["지속시간", "15"]
        ],
        "note": [
            "",
            ""
        ]
    }]
}