{
    "id": "demon_edge",
    "title": "악마의 검 Demon Edge",
    "desc": "피해 +46",
    "img": "data/images/items/demon_edge_lg.png",
    "cost": "2400",
    "story": "악마 대장장이 아브지디안이 만든 오래된 무기 중 하나입니다. 아브지디안은 칼날이 얼마나 예리한지 시험하던 도중 날에 베어 죽음을 맞았습니다.",
    "info": "",
    "table": [
        ["피해", "+46"]
    ],
    "note": [],
    "ability": "",
    "affect": "",
    "type": "",
    "recipe": [],
    "upgrade": [
        ["monkey_king_bar", "data/images/items/monkey_king_bar_lg.png"],
        ["greater_crit", "data/images/items/greater_crit_lg.png"],
        ["rapier", "data/images/items/rapier_lg.png"]
    ]
}