{
    "id": "ethereal_blade",
    "title": "혼령의 검 Ethereal Blade",
    "desc": "민첩 +40, 힘 +10, 지능 +10",
    "img": "data/images/items/ethereal_blade_lg.png",
    "cost": "4900",
    "story": "에테르 폭발 - 자신과 목표 대상을 에테르 형상으로 변환합니다. 대상 유닛은 둔화되며 공격을 가하거나 공격을 받지 않습니다. 또한 대상에게 자신의 주 능력치 X 2.0 + 75의 피해를 줍니다.",
    "info": "에테르 폭발 - 자신과 목표 대상을 에테르 형상으로 변환합니다. 대상 유닛은 둔화되며 공격을 가하거나 공격을 받지 않습니다. 또한 대상에게 자신의 주 능력치 X 2.0 + 75의 피해를 줍니다.",
    "table": [
        ["마나", "4"],
        ["쿨다운", "4"]
    ],
    "note": [
        "100MP / 30s",
        "공격을 받으면 마나 재생이 중단된다.",
        "1초당 33마나 재생"
    ],
    "ability": "지정된 대상(더블 클릭시 자신에게 적용)",
    "affect": "아군",
    "type": "마법 또는 일반   ",
    "recipe": [
        ["clarity", "data/images/items/clarity_lg.png"],
        ["bfury", "data/images/items/bfury_lg.png"],
        ["blink", "data/images/items/blink_lg.png"]
    ],
    "upgrade": []
}